LICENSE
MANIFEST.in
README.md
requirements.txt
setup.py
dj_db_conn_pool/__init__.py
dj_db_conn_pool/backends/__init__.py
dj_db_conn_pool/backends/mysql/__init__.py
dj_db_conn_pool/backends/mysql/base.py
dj_db_conn_pool/backends/oracle/__init__.py
dj_db_conn_pool/backends/oracle/base.py
dj_db_conn_pool/backends/postgresql/__init__.py
dj_db_conn_pool/backends/postgresql/base.py
dj_db_conn_pool/core/__init__.py
dj_db_conn_pool/core/exceptions.py
dj_db_conn_pool/core/mixins.py
django_db_connection_pool_plus.egg-info/PKG-INFO
django_db_connection_pool_plus.egg-info/SOURCES.txt
django_db_connection_pool_plus.egg-info/dependency_links.txt
django_db_connection_pool_plus.egg-info/requires.txt
django_db_connection_pool_plus.egg-info/top_level.txt