Metadata-Version: 2.1
Name: django-db-connection-pool-plus
Version: 1.0.7
Summary: Persistent database connection backends for Django
Home-page: https://github.com/HQ1363/django-db-connection-pool
Author: Altair Bow
Author-email: altair.bow@foxmail.com
License: MIT
Download-URL: https://pypi.python.org/pypi/django-db-connection-pool-plus/
Keywords: django,db,database,persistent,connection,pool
Platform: UNKNOWN
Classifier: Development Status :: 5 - Production/Stable
Classifier: Environment :: Web Environment
Classifier: Framework :: Django
Classifier: Intended Audience :: Developers
Classifier: License :: OSI Approved :: MIT License
Classifier: Operating System :: OS Independent
Classifier: Programming Language :: Python :: 3
Classifier: Topic :: Software Development :: Libraries :: Python Modules
Provides-Extra: mysql
Provides-Extra: oracle
Provides-Extra: all
Provides-Extra: postgresql
